getjswords.py
getjswords-0.0.2.dist-info/METADATA
getjswords-0.0.2.dist-info/WHEEL
getjswords-0.0.2.dist-info/entry_points.txt
getjswords-0.0.2.dist-info/top_level.txt
getjswords-0.0.2.dist-info/RECORD
