Metadata-Version: 2.1
Name: getjswords
Version: 0.0.2
Summary: get JS Words
Author-email: Nguyen Khanh Thuan <khanhthuan1995@gmail.com>
Project-URL: Homepage, https://github.com/khanhthuan1995/getjswords
Project-URL: Bug Tracker, https://github.com/khanhthuan1995/getjswords/issues
Classifier: Programming Language :: Python :: 3
Classifier: License :: OSI Approved :: MIT License
Classifier: Operating System :: OS Independent
Requires-Python: >=3.7
Requires-Dist: jsbeautifier
Requires-Dist: requests
Requires-Dist: urllib3
